tshistory_formula/__init__.py
tshistory_formula/api.py
tshistory_formula/cli.py
tshistory_formula/decorator.py
tshistory_formula/evaluator.py
tshistory_formula/funcs.py
tshistory_formula/gfuncs.py
tshistory_formula/helper.py
tshistory_formula/http.py
tshistory_formula/interpreter.py
tshistory_formula/migrate.py
tshistory_formula/registry.py
tshistory_formula/schema.py
tshistory_formula/schema.sql
tshistory_formula/search.py
tshistory_formula/testutil.py
tshistory_formula/tsio.py
tshistory_formula/types.py
tshistory_formula-0.16.2.dist-info/LICENSE
tshistory_formula-0.16.2.dist-info/METADATA
tshistory_formula-0.16.2.dist-info/WHEEL
tshistory_formula-0.16.2.dist-info/entry_points.txt
tshistory_formula-0.16.2.dist-info/top_level.txt
tshistory_formula-0.16.2.dist-info/RECORD
