Metadata-Version: 2.1
Name: tshistory_formula
Version: 0.16.2
Summary: Computed timeseries plugin for `tshistory`
Home-page: https://hg.sr.ht/~pythonian/tshistory_formula
Author: Pythonian
Author-email: aurelien.campeas@pythonian.fr
Classifier: Development Status :: 4 - Beta
Classifier: Intended Audience :: Developers
Classifier: License :: OSI Approved :: GNU Lesser General Public License v3 (LGPLv3)
Classifier: Operating System :: OS Independent
Classifier: Programming Language :: Python :: 3
Classifier: Topic :: Database
Classifier: Topic :: Scientific/Engineering
Classifier: Topic :: Software Development :: Version Control
License-File: LICENSE
Requires-Dist: tshistory >=0.20.0
Requires-Dist: holidays ==0.51
Requires-Dist: pycountry >=22.3.5
Requires-Dist: psyl >=0.8
